MUX_4X1.v
module MUX_4X1 
(
    input   wire    [1:0]   Sel     ,
    input   wire            In0     ,
    input   wire            In1     ,
    input   wire            In2     ,
    input   wire            In3     ,

    output  reg             MUX_OUT     
);

always @(*) 
    begin
        case (Sel)
            2'b00: MUX_OUT <= In0   ;
            2'b01: MUX_OUT <= In1   ;
            2'b10: MUX_OUT <= In2   ;
            2'b11: MUX_OUT <= In3   ;
            
            default: MUX_OUT <= In0   ;
        endcase    
    end
    
endmodule

ParityCalc.v
module ParityCalc 
(
    input   wire [7:0]  P_DATA      ,
    input   wire        PAR_TYP     ,

    output  wire        par_bit
);

assign  par_bit = ^P_DATA ^ PAR_TYP     ;
    
endmodule

FSM_Tx.v
module FSM_Tx 
(
    input   wire            Data_valid  ,
    input   wire            PAR_EN      ,
    input   wire            ser_done    ,
    input   wire            rst         ,
    input   wire            CLK         ,

    output  reg     [1:0]   mux_sel     ,
    output  reg             ser_en      ,
    output  reg             busy    
);

localparam  start_bit_sel   =   2'b00   ,
            stop_bit_sel    =   2'b01   ,
            ser_data_sel    =   2'b10   ,
            par_bit_sel     =   2'b11   ;

localparam  IDLE    = 3'b000 ,
            S0      = 3'b001 ,
            S1      = 3'b010 ,
            S2      = 3'b011 ,
            S3      = 3'b100 ;
            
reg     [2:0]   current_state   ;
reg     [2:0]   next_state      ;

always @(posedge CLK,negedge rst) 
    begin
        if (!rst)
            begin
                current_state   <= IDLE         ;   
            end
        else
            begin
                current_state   <= next_state   ;
            end
    end

always @(*) 
    begin
        case (current_state)
            IDLE :
                begin
                    if (Data_valid)
                        begin
                            next_state <= S0    ;
                        end
                    else
                        begin
                            next_state <= IDLE  ;
                        end
                end 

            S0      :
                begin
                    begin
                    next_state  <= S1   ;
                    end
                end

            S1      :
                begin
                    if (ser_done)
                        begin
                            if (PAR_EN)
                                begin
                                    next_state  <= S2   ;
                                end
                            else
                                begin
                                    next_state  <= S3   ;
                                end
                        end
                    else
                        begin
                            next_state  <= S1   ; 
                        end
                end

            S2 :
                begin
                    next_state  <= S3   ;
                end

            S3 :
                begin
                    if (Data_valid)
                        begin
                            next_state  <= S0   ; 
                        end
                    else
                        begin
                            next_state  <= IDLE ;
                        end
                end

            default: next_state <= IDLE ;
        endcase
    end

always @(*) 
    begin
        case (current_state)
            IDLE    :
                begin
                    mux_sel     <= stop_bit_sel     ;
                    ser_en      <= 1'b0             ;
                    busy        <= 1'b0             ;
                end

            S0      :
                begin
                    mux_sel     <= start_bit_sel    ;
                    ser_en      <= 1'b1             ;
                    busy        <= 1'b1             ;
                end

            S1      :
                begin
                    mux_sel     <= ser_data_sel     ;
                    ser_en      <= 1'b1             ;
                    busy        <= 1'b1             ;
                end

            S2      :
                begin
                    mux_sel     <= par_bit_sel      ;
                    ser_en      <= 1'b0             ;
                    busy        <= 1'b1             ;
                end

            S3      :
                begin
                    mux_sel     <= stop_bit_sel     ;
                    ser_en      <= 1'b0             ;
                    busy        <= 1'b1             ;
                end

            default :
                begin
                    mux_sel     <= stop_bit_sel     ;
                    ser_en      <= 1'b0             ;
                    busy        <= 1'b0             ;
                end 
        endcase        
    end

endmodule

Serializer.v
module Serializer 
(
    input   wire    [7:0]   P_DATA      ,
    input   wire            ser_en      ,
    input   wire            rst         ,
    input   wire            CLK         ,

    output  wire            ser_data    ,
    output  wire            ser_done     
);

reg     [3:0]   counter     ;
reg     [7:0]   data        ;

always @(posedge CLK, negedge rst) 
    begin
        if (!rst)
            begin
                counter <= 4'd0     ;
                data    <= 7'd0     ;
            end
        else if (ser_en)
            begin
                if (counter == 4'b0000)
                    begin
                        data        <= P_DATA           ;
                        counter     <= counter + 4'b1   ;
                    end
                else if (counter[3] == 1'b0 ) // counter is less than 8
                    begin
                        data        <= data >> 4'b1     ;
                        counter     <= counter + 4'b1   ;
                    end
                else
                    begin
                        counter     <= 4'b0000          ;
                    end
                end  
    end

assign  ser_done = counter[3]   ;
assign  ser_data = data [0]     ;
    
endmodule

UART_Tx.v
module UART_Tx 
(
    input   wire  [7:0] P_DATA      ,
    input   wire        PAR_EN      ,
    input   wire        Data_valid  ,
    input   wire        rst         ,
    input   wire        CLK         ,
    input   wire        PAR_TYP     ,

    output  wire        TX_OUT      ,
    output  wire        busy
);

localparam  start_bit   =   1'b0    ,
            stop_bit    =   1'b1    ;

/****************INTERNAL SIGNALS****************/
wire            ser_data    ;
wire            ser_en      ;
wire            ser_done    ;
wire    [1:0]   mux_sel     ;
wire            par_bit     ;


/************************************************/
/******************_SERIALIZER_******************/
/************************************************/
/*    
    input   wire    [7:0]   P_DATA      ,
    input   wire            ser_en      ,
    input   wire            rst         ,
    input   wire            CLK         ,

    output  wire            ser_data    ,
    output  wire            ser_done     
*/
Serializer SerializerTX
(
    .P_DATA     (P_DATA)        ,
    .ser_en     (ser_en)        ,
    .rst        (rst)           ,
    .CLK        (CLK)           ,

    .ser_data   (ser_data)      ,
    .ser_done   (ser_done)
);


/************************************************/
/*********************_FSM_**********************/
/************************************************/
/*
    input   wire            Data_valid  ,
    input   wire            PAR_EN      ,
    input   wire            ser_done    ,
    input   wire            rst         ,
    input   wire            CLK         ,

    output  reg     [1:0]   mux_sel     ,
    output  reg             ser_en      ,
    output  reg             busy    
*/
FSM_Tx FSMTX
(
    .Data_valid (Data_valid)    ,
    .PAR_EN     (PAR_EN)        ,
    .ser_done   (ser_done)      ,
    .rst        (rst)           ,
    .CLK        (CLK)           ,

    .mux_sel    (mux_sel)       ,
    .ser_en     (ser_en)        ,
    .busy       (busy)      
);


/************************************************/
/***************_ParityCalculator_***************/
/************************************************/
/*
    input   wire [7:0]  P_DATA      ,
    input   wire        PAR_TYP     ,

    output  wire        par_bit
*/
ParityCalc ParCalcTX
(
    .P_DATA     (P_DATA)    ,
    .PAR_TYP    (PAR_TYP)   ,

    .par_bit    (par_bit)   
);

/************************************************/
/*********************_MUX_**********************/
/************************************************/
/*
    input   wire    [1:0]   Sel     ,
    input   wire            In0     ,
    input   wire            In1     ,
    input   wire            In2     ,
    input   wire            In3     ,

    output  reg             MUX_OUT    
*/
MUX_4X1 MUX_TX
(
    .Sel    (mux_sel)   ,
    .In0    (start_bit) ,
    .In1    (stop_bit)  ,
    .In2    (ser_data)  ,
    .In3    (par_bit)   ,

    .MUX_OUT    (TX_OUT)
);

endmodule

UART_Tx_tb.v
`timescale 1ns/100ps

module UART_Tx_tb ();

    /***************Testbench signals***************/
    reg     [7:0]   P_DATA_tb       ;
    reg             PAR_EN_tb       ;
    reg             Data_valid_tb   ;
    reg             rst_tb          ;
    reg             CLK_tb          ;
    reg             PAR_TYP_tb      ;

    wire            TX_OUT_tb       ;
    wire            busy_tb         ;
    
    /***************Clock Variables***************/
    localparam  CLK_PERIOD = 5                  ;
    always #(0.5*CLK_PERIOD) CLK_tb = ~CLK_tb   ;

    /**************Desgin under test**************/
    UART_Tx DUT
    (
        .P_DATA         (P_DATA_tb)         ,
        .PAR_EN         (PAR_EN_tb)         ,
        .Data_valid     (Data_valid_tb)     ,
        .rst            (rst_tb)            ,
        .CLK            (CLK_tb)            ,
        .PAR_TYP        (PAR_TYP_tb)        ,

        .TX_OUT         (TX_OUT_tb)         ,
        .busy           (busy_tb)
    );

    initial 
        begin
            $dumpfile ("UART_Tx_tb.vcd")    ;
            $dumpvars                       ;

            rst_tb          =   1'b1    ;
            CLK_tb          =   1'b0    ;
            Data_valid_tb   =   1'b0    ;   

            #(0.2*CLK_PERIOD)
            rst_tb          =   1'b0    ;

            #(0.5*CLK_PERIOD)
            rst_tb          =   1'b1    ;

            #CLK_PERIOD
            P_DATA_tb       =   8'b11010101 ;
            PAR_EN_tb       =   1'b0        ;
            Data_valid_tb   =   1'b1        ;

            #CLK_PERIOD
            if (TX_OUT_tb == 1'b0)
                begin
                    $display ("Test1: PASSED : Start bit works fine");
                end
            else
                begin
                    $display ("Test1: FAILED : There is a problem in the start bit");
                end

            #CLK_PERIOD
            if (TX_OUT_tb == 1'b1)
                begin
                    $display ("Test2: PASSED : LSB works fine");
                end
            else
                begin
                    $display ("Test2: FAILED : There is a problem in the LSB");
                end

            #(CLK_PERIOD*5)
            if (TX_OUT_tb == 1'b0)
                begin
                    $display ("Test3: PASSED : sixth bit works fine");
                end
            else
                begin
                    $display ("Test3: FAILED : There is a problem in the sixth bit");
                end

            #(CLK_PERIOD*3)
            if (TX_OUT_tb == 1'b1)
                begin
                    $display ("Test4: PASSED : stop bit works fine");
                end
            else
                begin
                    $display ("Test4: FAILED : There is a problem in the stop bit");
                end

            P_DATA_tb       =   8'b00000001 ;
            PAR_EN_tb       =   1'b1        ;
            PAR_TYP_tb      =   1'b0        ; // even parity

            #(CLK_PERIOD)
            if (TX_OUT_tb == 1'b0)
                begin
                    $display ("Test5: PASSED : start bit for second trial works fine");
                end
            else
                begin
                    $display ("Test5: FAILED : There is a problem in the start bit of the second trial");
                end
            
            #(CLK_PERIOD)
            if (TX_OUT_tb == 1'b1)
                begin
                    $display ("Test5: PASSED : first bit for second trial works fine");
                end
            else
                begin
                    $display ("Test5: FAILED : There is a problem in the first bit of the second trial");
                end

            #(CLK_PERIOD*7)
            if (TX_OUT_tb == 1'b0)
                begin
                    $display ("Test6: PASSED : MSB bit for second trial works fine");
                end
            else
                begin
                    $display ("Test6: FAILED : There is a problem in the MSB of the second trial");
                end

            Data_valid_tb   = 1'b0  ;

            #(CLK_PERIOD)
            if (TX_OUT_tb == 1'b1)
                begin
                    $display ("Test7: PASSED : parity bit for second trial works fine");
                end
            else
                begin
                    $display ("Test7: FAILED : There is a problem in the parity bit of the second trial");
                end

            #(CLK_PERIOD)
            if (TX_OUT_tb == 1'b1)
                begin
                    $display ("Test8: PASSED : stop bit for second trial works fine");
                end
            else
                begin
                    $display ("Test8: FAILED : There is a problem in the stop bit of the second trial");
                end

            #(CLK_PERIOD)
            if (TX_OUT_tb == 1'b1)
                begin
                    $display ("Test9: PASSED : IDLE bit after second trial works fine");
                end
            else
                begin
                    $display ("Test9: FAILED : There is a problem in the IDLE bit after the second trial");
                end

            #(CLK_PERIOD*5)
            if (TX_OUT_tb == 1'b1)
                begin
                    $display ("Test10: PASSED : IDLE bit still works fine");
                end
            else
                begin
                    $display ("Test10: FAILED : There is a problem in the IDLE bit after a while");
                end


            #(CLK_PERIOD*10)
            $finish     ;

        end

endmodule

UART_Tx_tb.vcd
$date
	Thu Jul 07 11:21:25 2022
$end
$version
	ModelSim Version 10.5b
$end
$timescale
	100ps
$end

$scope module UART_Tx_tb $end
$var parameter 32 ! CLK_PERIOD $end
$var reg 8 " P_DATA_tb [7:0] $end
$var reg 1 # PAR_EN_tb $end
$var reg 1 $ Data_valid_tb $end
$var reg 1 % rst_tb $end
$var reg 1 & CLK_tb $end
$var reg 1 ' PAR_TYP_tb $end
$var wire 1 ( TX_OUT_tb $end
$var wire 1 ) busy_tb $end

$scope module DUT $end
$var parameter 1 * start_bit $end
$var parameter 1 + stop_bit $end
$var wire 1 , P_DATA [7] $end
$var wire 1 - P_DATA [6] $end
$var wire 1 . P_DATA [5] $end
$var wire 1 / P_DATA [4] $end
$var wire 1 0 P_DATA [3] $end
$var wire 1 1 P_DATA [2] $end
$var wire 1 2 P_DATA [1] $end
$var wire 1 3 P_DATA [0] $end
$var wire 1 4 PAR_EN $end
$var wire 1 5 Data_valid $end
$var wire 1 6 rst $end
$var wire 1 7 CLK $end
$var wire 1 8 PAR_TYP $end
$var wire 1 ( TX_OUT $end
$var wire 1 ) busy $end
$var wire 1 9 ser_data $end
$var wire 1 : ser_en $end
$var wire 1 ; ser_done $end
$var wire 1 < mux_sel [1] $end
$var wire 1 = mux_sel [0] $end
$var wire 1 > par_bit $end

$scope module SerializerTX $end
$var wire 1 , P_DATA [7] $end
$var wire 1 - P_DATA [6] $end
$var wire 1 . P_DATA [5] $end
$var wire 1 / P_DATA [4] $end
$var wire 1 0 P_DATA [3] $end
$var wire 1 1 P_DATA [2] $end
$var wire 1 2 P_DATA [1] $end
$var wire 1 3 P_DATA [0] $end
$var wire 1 : ser_en $end
$var wire 1 6 rst $end
$var wire 1 7 CLK $end
$var wire 1 9 ser_data $end
$var wire 1 ; ser_done $end
$var reg 4 ? counter [3:0] $end
$var reg 8 @ data [7:0] $end
$upscope $end

$scope module FSMTX $end
$var parameter 2 A start_bit_sel $end
$var parameter 2 B stop_bit_sel $end
$var parameter 2 C ser_data_sel $end
$var parameter 2 D par_bit_sel $end
$var parameter 3 E IDLE $end
$var parameter 3 F S0 $end
$var parameter 3 G S1 $end
$var parameter 3 H S2 $end
$var parameter 3 I S3 $end
$var wire 1 5 Data_valid $end
$var wire 1 4 PAR_EN $end
$var wire 1 ; ser_done $end
$var wire 1 6 rst $end
$var wire 1 7 CLK $end
$var reg 2 J mux_sel [1:0] $end
$var reg 1 K ser_en $end
$var reg 1 L busy $end
$var reg 3 M current_state [2:0] $end
$var reg 3 N next_state [2:0] $end
$upscope $end

$scope module ParCalcTX $end
$var wire 1 , P_DATA [7] $end
$var wire 1 - P_DATA [6] $end
$var wire 1 . P_DATA [5] $end
$var wire 1 / P_DATA [4] $end
$var wire 1 0 P_DATA [3] $end
$var wire 1 1 P_DATA [2] $end
$var wire 1 2 P_DATA [1] $end
$var wire 1 3 P_DATA [0] $end
$var wire 1 8 PAR_TYP $end
$var wire 1 > par_bit $end
$upscope $end

$scope module MUX_TX $end
$var wire 1 < Sel [1] $end
$var wire 1 = Sel [0] $end
$var wire 1 O In0 $end
$var wire 1 P In1 $end
$var wire 1 9 In2 $end
$var wire 1 > In3 $end
$var reg 1 Q MUX_OUT $end
$upscope $end
$upscope $end
$upscope $end
$enddefinitions $end
#0
$dumpvars
bx "
x#
0$
1%
0&
x'
bx ?
bx @
bx J
xK
xL
bx M
b0 N
0Q
b101 !
b0 *
b1 +
b0 A
b1 B
b10 C
b11 D
b0 E
b1 F
b10 G
b11 H
b100 I
0(
x)
x9
x:
x;
x=
x<
x>
x8
07
16
05
x4
x3
x2
x1
x0
x/
x.
x-
x,
1P
0O
$end
#10
0%
06
b0 ?
b0 @
b0 M
0;
09
b1 J
0K
0L
0:
0)
1=
0<
1Q
1(
#25
1&
17
#35
1%
16
#50
0&
07
#75
1&
17
#85
b11010101 "
0#
1$
13
02
11
00
1/
0.
1-
1,
04
15
b1 N
#100
0&
07
#125
1&
17
b1 M
b10 N
b0 J
1K
1L
1:
1)
0=
0Q
0(
#150
0&
07
#175
1&
17
b11010101 @
b1 ?
b10 M
19
b10 J
1<
1Q
1(
#200
0&
07
#225
1&
17
b1101010 @
b10 ?
09
0Q
0(
#250
0&
07
#275
1&
17
b110101 @
b11 ?
19
1Q
1(
#300
0&
07
#325
1&
17
b11010 @
b100 ?
09
0Q
0(
#350
0&
07
#375
1&
17
b1101 @
b101 ?
19
1Q
1(
#400
0&
07
#425
1&
17
b110 @
b110 ?
09
0Q
0(
#450
0&
07
#475
1&
17
b11 @
b111 ?
19
1Q
1(
#500
0&
07
#525
1&
17
b1 @
b1000 ?
1;
b100 N
#550
0&
07
#575
1&
17
b0 ?
b100 M
0;
b1 N
b1 J
0K
0:
1=
0<
#585
b1 "
1#
0'
01
0/
0-
0,
08
14
1>
#600
0&
07
#625
1&
17
b1 M
b10 N
b0 J
1K
1:
0=
0Q
0(
#650
0&
07
#675
1&
17
b1 ?
b10 M
b10 J
1<
1Q
1(
#700
0&
07
#725
1&
17
b0 @
b10 ?
09
0Q
0(
#750
0&
07
#775
1&
17
b11 ?
#800
0&
07
#825
1&
17
b100 ?
#850
0&
07
#875
1&
17
b101 ?
#900
0&
07
#925
1&
17
b110 ?
#950
0&
07
#975
1&
17
b111 ?
#1000
0&
07
#1025
1&
17
b1000 ?
1;
b11 N
#1035
0$
05
#1050
0&
07
#1075
1&
17
b0 ?
b11 M
0;
b100 N
b11 J
0K
0:
1=
1Q
1(
#1100
0&
07
#1125
1&
17
b